langchain_lambdadb/__init__.py
langchain_lambdadb/py.typed
langchain_lambdadb/vectorstores.py
langchain_lambdadb-0.1.0.dist-info/LICENSE
langchain_lambdadb-0.1.0.dist-info/METADATA
langchain_lambdadb-0.1.0.dist-info/WHEEL
langchain_lambdadb-0.1.0.dist-info/RECORD
