Metadata-Version: 2.3
Name: langchain-lambdadb
Version: 0.1.0
Summary: An integration package connecting LambdaDB and LangChain
License: MIT
Requires-Python: >=3.9.2,<4.0
Classifier: License :: OSI Approved :: MIT License
Classifier: Programming Language :: Python :: 3
Classifier: Programming Language :: Python :: 3.10
Classifier: Programming Language :: Python :: 3.11
Classifier: Programming Language :: Python :: 3.12
Classifier: Programming Language :: Python :: 3.13
Requires-Dist: lambdadb (>=0.5.11,<0.6.0)
Requires-Dist: langchain-core (>=0.3.15,<0.4.0)
Project-URL: Repository, https://github.com/lambdadb/langchain-lambdadb
Project-URL: Release Notes, https://github.com/lambdadb/langchain-lambdadb/releases
Project-URL: Source Code, https://github.com/lambdadb/langchain-lambdadb/tree/develop/langchain_lambdadb
